igann/__init__.py
igann/igann.py
igann/igannSklearn.py
igann/igann_bagged.py
igann/igann_interactive.py
igann-0.1.7.dist-info/LICENSE
igann-0.1.7.dist-info/METADATA
igann-0.1.7.dist-info/WHEEL
igann-0.1.7.dist-info/top_level.txt
igann-0.1.7.dist-info/RECORD
