Metadata-Version: 2.1
Name: igann
Version: 0.1.7
Summary: Implementation of Interpretable Generalized Additive Neural Networks
Home-page: https://github.com/MathiasKraus/igann
Author: Mathias Kraus
Author-email: mathias.sebastian.kraus@gmail.com
License: MIT
License-File: LICENSE
Requires-Dist: numpy
Requires-Dist: pandas
Requires-Dist: scikit-learn
Requires-Dist: torch>=1.9.0
Requires-Dist: matplotlib
Requires-Dist: seaborn
